openledger/__init__.py
openledger/banks/__init__.py
openledger/banks/client.py
openledger/banks/raw_client.py
openledger/banks/types/__init__.py
openledger/banks/types/get_v1banks_create_link_response.py
openledger/banks/types/put_v1banks_accounts_response.py
openledger/banks/types/put_v1banks_accounts_response_created_accounts_item.py
openledger/categories/__init__.py
openledger/categories/client.py
openledger/categories/raw_client.py
openledger/categories/types/__init__.py
openledger/categories/types/get_v1categories_response.py
openledger/categories/types/get_v1categories_response_categories_item.py
openledger/categories/types/get_v1categories_response_categories_item_type.py
openledger/categories/types/post_v1categories_request_type.py
openledger/categories/types/post_v1categories_response.py
openledger/categories/types/post_v1categories_response_category.py
openledger/client.py
openledger/core/__init__.py
openledger/core/api_error.py
openledger/core/client_wrapper.py
openledger/core/datetime_utils.py
openledger/core/file.py
openledger/core/force_multipart.py
openledger/core/http_client.py
openledger/core/http_response.py
openledger/core/jsonable_encoder.py
openledger/core/pydantic_utilities.py
openledger/core/query_encoder.py
openledger/core/remove_none_from_dict.py
openledger/core/request_options.py
openledger/core/serialization.py
openledger/developers/__init__.py
openledger/developers/client.py
openledger/developers/raw_client.py
openledger/developers/types/__init__.py
openledger/developers/types/post_v1developers_auth_generate_token_response.py
openledger/entities/__init__.py
openledger/entities/client.py
openledger/entities/raw_client.py
openledger/entities/types/__init__.py
openledger/entities/types/delete_v1entities_response.py
openledger/entities/types/get_v1entities_response.py
openledger/entities/types/get_v1entities_response_entity.py
openledger/entities/types/get_v1entities_response_entity_address.py
openledger-4.20.4.dist-info/METADATA
openledger-4.20.4.dist-info/WHEEL
openledger-4.20.4.dist-info/RECORD
